minreq/__init__.py
minreq/curl.py
minreq/actions.py
minreq/requester.py
minreq/differs.py
minreq/utils.py
minreq/cmdline.py
minreq-0.1.0.dist-info/metadata.json
minreq-0.1.0.dist-info/top_level.txt
minreq-0.1.0.dist-info/METADATA
minreq-0.1.0.dist-info/RECORD
minreq-0.1.0.dist-info/entry_points.txt
minreq-0.1.0.dist-info/DESCRIPTION.rst
minreq-0.1.0.dist-info/WHEEL
