Metadata-Version: 2.0
Name: minreq
Version: 0.1.0
Summary: Check required data in a request.
Home-page: https://github.com/csalazar/minreq
Author: Claudio Salazar
Author-email: csalazar@spect.cl
License: BSD
Keywords: minreq
Platform: UNKNOWN
Classifier: Development Status :: 2 - Pre-Alpha
Classifier: Intended Audience :: Developers
Classifier: Programming Language :: Python :: 2
Classifier: Programming Language :: Python :: 2.6
Classifier: Programming Language :: Python :: 2.7
Requires-Dist: requests
